[
  {
    "CdsFCBContext": "{\"FileType\":true,\"ImageExternalStorage\":true}",
    "EntitySetName": "cr282_dl_san_pham_ql_khacs",
    "IsHidden": false,
    "IsSampleData": false,
    "IsWritable": true,
    "LogicalName": "cr282_dl_san_pham_ql_khac",
    "MaxGetRowsCount": 2000,
    "Name": "DL_SAN_PHAM_QL_KHACS",
    "NativeCDSDataSourceInfoNameMapping": {
      "_ownerid_value": "Owner",
      "cr282_dl_san_pham_ql_khac_AsyncOperations": "System Jobs",
      "cr282_dl_san_pham_ql_khac_BulkDeleteFailures": "Bulk Delete Failures",
      "cr282_dl_san_pham_ql_khac_MailboxTrackingFolders": "Mailbox Auto Tracking Folders",
      "cr282_dl_san_pham_ql_khac_PrincipalObjectAttributeAccesses": "Field Sharing",
      "cr282_dl_san_pham_ql_khac_ProcessSession": "Process Sessions",
      "cr282_dl_san_pham_ql_khac_SyncErrors": "Sync Errors",
      "cr282_dl_san_pham_ql_khacid": "DL_SAN_PHAM_QL_KHAC",
      "cr282_ma_dl": "MA_DL",
      "cr282_ma_nhom_ql": "MA_NHOM_QL",
      "cr282_ma_sp": "MA_SP",
      "cr282_mo_ta": "MO_TA",
      "createdby": "Created By",
      "createdon": "Created On",
      "createdonbehalfby": "Created By (Delegate)",
      "importsequencenumber": "Import Sequence Number",
      "modifiedby": "Modified By",
      "modifiedon": "Modified On",
      "modifiedonbehalfby": "Modified By (Delegate)",
      "overriddencreatedon": "Record Created On",
      "owningbusinessunit": "Owning Business Unit",
      "owningteam": "Owning Team",
      "owninguser": "Owning User",
      "statecode": "Status",
      "statuscode": "Status Reason",
      "timezoneruleversionnumber": "Time Zone Rule Version Number",
      "utcconversiontimezonecode": "UTC Conversion Time Zone Code",
      "versionnumber": "Version Number"
    },
    "PreferredName": "DL_SAN_PHAM_QL_KHACS",
    "Type": "NativeCDSDataSourceInfo"
  },
  {
    "DisplayName": "DL_SAN_PHAM_QL_KHACS (Views)",
    "Name": "_cr282_dl_san_pham_ql_khac_views",
    "RelatedEntityName": "DL_SAN_PHAM_QL_KHACS",
    "TrimmedViewName": true,
    "Type": "ViewInfo",
    "ViewInfoNameMapping": {
      "0d6e50c9-dfb1-41ca-b27e-043f6021187b": "DL_SAN_PHAM_QL_KHAC Lookup View",
      "3ac8b13e-ed0b-44f7-ae2e-b3bb178de921": "Inactive DL_SAN_PHAM_QL_KHACS",
      "c4b676bd-3c98-4086-9478-9c32bbbaa835": "DL_SAN_PHAM_QL_KHAC Associated View",
      "d402f5db-1ff2-48e4-974a-c26e97a9984d": "Active DL_SAN_PHAM_QL_KHACS",
      "fc416394-e59d-4f60-8d58-6a058fe06d36": "DL_SAN_PHAM_QL_KHAC Advanced Find View"
    }
  },
  {
    "DisplayName": "Status (DL_SAN_PHAM_QL_KHACS)",
    "Name": "cr282_dl_san_pham_ql_khac_statecode",
    "OptionSetInfoNameMapping": {
      "0": "Active",
      "1": "Inactive"
    },
    "OptionSetIsBooleanValued": false,
    "OptionSetIsGlobal": false,
    "OptionSetReference": {
      "OptionSetReferenceItem0": {
        "OptionSetReferenceColumnName": "statecode",
        "OptionSetReferenceEntityName": "DL_SAN_PHAM_QL_KHACS"
      }
    },
    "OptionSetTypeKey": "StateType",
    "RelatedColumnInvariantName": "statecode",
    "RelatedEntityName": "DL_SAN_PHAM_QL_KHACS",
    "Type": "OptionSetInfo"
  },
  {
    "DisplayName": "Status Reason (DL_SAN_PHAM_QL_KHACS)",
    "Name": "cr282_dl_san_pham_ql_khac_statuscode",
    "OptionSetInfoNameMapping": {
      "1": "Active",
      "2": "Inactive"
    },
    "OptionSetIsBooleanValued": false,
    "OptionSetIsGlobal": false,
    "OptionSetReference": {
      "OptionSetReferenceItem0": {
        "OptionSetReferenceColumnName": "statuscode",
        "OptionSetReferenceEntityName": "DL_SAN_PHAM_QL_KHACS"
      }
    },
    "OptionSetTypeKey": "StatusType",
    "RelatedColumnInvariantName": "statuscode",
    "RelatedEntityName": "DL_SAN_PHAM_QL_KHACS",
    "Type": "OptionSetInfo"
  }
]